Workbook

Sheet Dashboard
A1: COMPLETE FINANCIAL PLANNING DASHBOARD
A3: PROFILE | E3: Final Value
A4: Current Age | B4: 35 | C4: years | E4: Emergency Fund Target | F4: =B6*B8 -> 300000
A5: Monthly Salary | B5: 50000 | C5: ₹ | E5: Months Needed @ Full Surplus | F5: =ROUNDUP(F4/B7,0) -> 12
A6: Monthly Expenses | B6: 25000 | C6: ₹ | E6: Suggested Term Cover (20x annual income) | F6: =B5*12*20 -> 12000000
A7: Monthly Surplus | B7: =B5-B6 -> 25000 | C7: ₹ | E7: Suggested Term Cover (25x annual income) | F7: =B5*12*25 -> 15000000
A8: Emergency Fund Months | B8: 12 | C8: months | E8: Suggested Health Cover | F8: 2000000
A9: Retirement Age | B9: 60 | C9: years | E9: Years to Retirement | F9: =B9-B4 -> 25
E10: Retirement Corpus Estimate | F10: ='Retirement Planning'!E8 -> 25751224
A12: DISCLAIMER: ETF Names Educational illustration only. You can Edit Them This workbook does not constitute investment advice, insurance advice, or a recommendation.
E15: 1Cr Best Term Policy: | F15: https://bit.ly/_Term_Policy
E16: Best Health Policy | F16: https://bit.ly/_Health_Policy

Sheet Emergency Fund Plan
A1: 12-MONTH EMERGENCY FUND PLANNER
A3: Month | B3: Opening Balance | C3: Monthly Saving | D3: Interest / Buffer | E3: Total Added | F3: Closing Balance | G3: Target | H3: % of Target | J3: QUICK SUMMARY
A4: Month 1 | B4: 0 | C4: =Dashboard!B7 -> 25000 | D4: 0 | E4: =C4+D4 -> 25000 | F4: =B4+E4 -> 25000 | G4: =Dashboard!F4 -> 300000 | H4: =IF(G4=0,0,F4/G4) -> 0.083333333 | J4: Target Corpus | K4: =Dashboard!F4 -> 300000 | L4: ₹
A5: Month 2 | B5: =F4 -> 25000 | C5: =Dashboard!B7 -> 25000 | D5: 0 | E5: =C5+D5 -> 25000 | F5: =B5+E5 -> 50000 | G5: =Dashboard!F4 -> 300000 | H5: =IF(G5=0,0,F5/G5) -> 0.16666667 | J5: Monthly Saving Assumed | K5: =Dashboard!B7 -> 25000 | L5: ₹
A6: Month 3 | B6: =F5 -> 50000 | C6: =Dashboard!B7 -> 25000 | D6: 0 | E6: =C6+D6 -> 25000 | F6: =B6+E6 -> 75000 | G6: =Dashboard!F4 -> 300000 | H6: =IF(G6=0,0,F6/G6) -> 0.25 | J6: Balance After 12 Months | K6: =F15 -> 300000 | L6: ₹
A7: Month 4 | B7: =F6 -> 75000 | C7: =Dashboard!B7 -> 25000 | D7: 0 | E7: =C7+D7 -> 25000 | F7: =B7+E7 -> 100000 | G7: =Dashboard!F4 -> 300000 | H7: =IF(G7=0,0,F7/G7) -> 0.33333333 | J7: Gap After 12 Months | K7: =K4-K6 -> 0 | L7: ₹
A8: Month 5 | B8: =F7 -> 100000 | C8: =Dashboard!B7 -> 25000 | D8: 0 | E8: =C8+D8 -> 25000 | F8: =B8+E8 -> 125000 | G8: =Dashboard!F4 -> 300000 | H8: =IF(G8=0,0,F8/G8) -> 0.41666667 | J8: Months Needed to Fully Reach Target | K8: =Dashboard!F5 -> 12 | L8: months
A9: Month 6 | B9: =F8 -> 125000 | C9: =Dashboard!B7 -> 25000 | D9: 0 | E9: =C9+D9 -> 25000 | F9: =B9+E9 -> 150000 | G9: =Dashboard!F4 -> 300000 | H9: =IF(G9=0,0,F9/G9) -> 0.5
A10: Month 7 | B10: =F9 -> 150000 | C10: =Dashboard!B7 -> 25000 | D10: 0 | E10: =C10+D10 -> 25000 | F10: =B10+E10 -> 175000 | G10: =Dashboard!F4 -> 300000 | H10: =IF(G10=0,0,F10/G10) -> 0.58333333
A11: Month 8 | B11: =F10 -> 175000 | C11: =Dashboard!B7 -> 25000 | D11: 0 | E11: =C11+D11 -> 25000 | F11: =B11+E11 -> 200000 | G11: =Dashboard!F4 -> 300000 | H11: =IF(G11=0,0,F11/G11) -> 0.66666667
A12: Month 9 | B12: =F11 -> 200000 | C12: =Dashboard!B7 -> 25000 | D12: 0 | E12: =C12+D12 -> 25000 | F12: =B12+E12 -> 225000 | G12: =Dashboard!F4 -> 300000 | H12: =IF(G12=0,0,F12/G12) -> 0.75
A13: Month 10 | B13: =F12 -> 225000 | C13: =Dashboard!B7 -> 25000 | D13: 0 | E13: =C13+D13 -> 25000 | F13: =B13+E13 -> 250000 | G13: =Dashboard!F4 -> 300000 | H13: =IF(G13=0,0,F13/G13) -> 0.83333333
A14: Month 11 | B14: =F13 -> 250000 | C14: =Dashboard!B7 -> 25000 | D14: 0 | E14: =C14+D14 -> 25000 | F14: =B14+E14 -> 275000 | G14: =Dashboard!F4 -> 300000 | H14: =IF(G14=0,0,F14/G14) -> 0.91666667
A15: Month 12 | B15: =F14 -> 275000 | C15: =Dashboard!B7 -> 25000 | D15: 0 | E15: =C15+D15 -> 25000 | F15: =B15+E15 -> 300000 | G15: =Dashboard!F4 -> 300000 | H15: =IF(G15=0,0,F15/G15) -> 1

Sheet Guide
A1: IMPORTANCE OF DIVERSIFICATION
A2: INVESTMENT | B2: 10000
A3: Asset Class | B3: Allocation % | C3: Amount (₹) | D3: Purpose
A4: Nifty ETF | B4: 0.3 | C4: =B2*B4 -> 3000 | D4: Stability
A5: Mid Cap ETF | B5: 0.2 | C5: =B2*B5 -> 2000 | D5: Growth with Higher Risk
A6: Small Cap ETF | B6: 0.2 | C6: =B2*B6 -> 2000 | D6: High Growth with High Risk
A7: REIT / Real Estate | B7: 0.2 | C7: =B2*B7 -> 2000 | D7: Diversification & Rental Yield
A8: Gold ETF | B8: 0.1 | C8: =B2*B8 -> 1000 | D8: Inflation Protection & Equity Hedge
A10: Total Investment | B10: 1 | C10: =B2*B10 -> 10000

Sheet Investment Planning
A1: INVESTMENT PLANNING (AFTER EMERGENCY FUND & INSURANCE)
A3: Asset Class | B3: Allocation % | C3: Monthly SIP | D3: Expected CAGR | E3: Years | F3: Future Value | G3: Role in Portfolio | H3: Risk Level
A4: Nifty ETF | B4: 0.3 | C4: =ROUND(Dashboard!B7*B4,0) -> 7500 | D4: 0.1 | E4: 10 | F4: =IF(D4="",0,C4*(((1+D4/12)^(E4*12)-1)/(D4/12))*(1+D4/12)) -> 1549140.2 | G4: Core stability | H4: Moderate
A5: Mid Cap ETF | B5: 0.2 | C5: =ROUND(Dashboard!B7*B5,0) -> 5000 | D5: 0.12 | E5: 20 | F5: =IF(D5="",0,C5*(((1+D5/12)^(E5*12)-1)/(D5/12))*(1+D5/12)) -> 4995739.6 | G5: Growth | H5: Moderate-High
A6: Small Cap ETF | B6: 0.2 | C6: =ROUND(Dashboard!B7*B6,0) -> 5000 | D6: 0.14 | E6: 30 | F6: =IF(D6="",0,C6*(((1+D6/12)^(E6*12)-1)/(D6/12))*(1+D6/12)) -> 27785278 | G6: Aggressive growth | H6: High
A7: REIT / Real Estate | B7: 0.2 | C7: =ROUND(Dashboard!B7*B7,0) -> 5000 | D7: 0.09 | E7: 30 | F7: =IF(D7="",0,C7*(((1+D7/12)^(E7*12)-1)/(D7/12))*(1+D7/12)) -> 9222370.3 | G7: Diversification | H7: Moderate
A8: Gold ETF | B8: 0.1 | C8: =ROUND(Dashboard!B7*B8,0) -> 2500 | D8: 0.07 | E8: 30 | F8: =IF(D8="",0,C8*(((1+D8/12)^(E8*12)-1)/(D8/12))*(1+D8/12)) -> 3067718.7 | G8: Hedge | H8: Low-Moderate
A10: Total | B10: =SUM(B4:B8) -> 1 | C10: =SUM(C4:C8) -> 25000 | F10: =SUM(F4:F8) -> 46620247 | H10: Weighted Portfolio CAGR | I10: =SUMPRODUCT(B4:B8,D4:D8) -> 0.107
H11: Monthly Investable Amount | I11: =Dashboard!B7 -> 25000
H12: Projected 10-Year Corpus | I12: =F10 -> 46620247
H13: Note | I13: Assumes monthly SIP and constant CAGR

Sheet Retirement Planning
A1: RETIREMENT PLANNING MODEL
A3: Current Age | B3: =Dashboard!B4 -> 35 | D3: Metric | E3: Value | F3: Unit
A4: Retirement Age | B4: =Dashboard!B9 -> 60 | D4: Current Monthly Surplus | E4: =Dashboard!B7 -> 25000 | F4: ₹
A5: Years to Retirement | B5: =B4-B3 -> 25 | D5: Years to Retirement | E5: =B5 -> 25 | F5: years
A6: Current Monthly Expenses | B6: =Dashboard!B6 -> 25000 | D6: Assumed Monthly Retirement SIP Return | E6: =B8/12 -> 0.0091666667 | F6: rate
A7: Inflation Assumption | B7: 0.06 | D7: Required Monthly SIP | E7: =IF(E5=0,0,E8/((((1+E6)^(E5*12))-1)/E6)*(1/(1+E6))) -> 16189.821 | F7: ₹
A8: Expected Return Before Retirement | B8: 0.11 | D8: Corpus Target | E8: =B14 -> 25751224 | F8: ₹
A9: Expected Return After Retirement | B9: 0.07 | D9: Note | E9: Educational estimate based on assumptions
A10: Expense Replacement Ratio | B10: 0.8
A11: Monthly Expense Needed at Retirement | B11: =B6*(1+B7)^B5*B10 -> 85837.414 | D11: Sensitivity - Corpus @ 5% inflation | E11: =B6*(1+0.05)^B5*B10*12*B13 -> 20318130 | F11: ₹
A12: Annual Expense Needed at Retirement | B12: =B11*12 -> 1030049 | D12: Sensitivity - Corpus @ 7% inflation | E12: =B6*(1+0.07)^B5*B10*12*B13 -> 32564596 | F12: ₹
A13: Retirement Corpus Multiple (25x rule) | B13: 25
A14: Required Retirement Corpus | B14: =B12*B13 -> 25751224 | D14: Suggested Action | E14: Increase SIP with salary hikes each year
